{
  "start_date": "2026-06-15",
  "end_date": "2026-06-21",
  "stats": {
    "total_merged": 16,
    "total_reviews": 221,
    "total_threads": 21,
    "new_contributors": 1
  },
  "tldr": [
    "Significant technical exploration into novel blockchain data management strategies, specifically discussions around Fountain Codes, aiming to fundamentally reduce full node storage requirements and resource costs.",
    "Intensified focus on protocol-level advancements for privacy and scalability, highlighted by ongoing work on Pay-to-Many-Recipients (P2MR) and related public key recovery schemes, alongside discussions on more robust K-of-N Lightning Network node architectures."
  ],
  "categories": {
    "merged": [
      {
        "name": "\ud83d\udee0\ufe0f Build, CI & Testing",
        "prs": [
          {
            "number": 1860,
            "title": "cmake: Emulate Libtool's behavior on NetBSD and OpenBSD",
            "author": {
              "username": "hebasto",
              "uuid": "can_hennadii_stepanov"
            },
            "summary": "This improves the build process for Bitcoin Core on NetBSD and OpenBSD by emulating Libtool's behavior.",
            "importance": 21
          },
          {
            "number": 35441,
            "title": "ci: inline runner selection",
            "author": {
              "username": "willcl-ark",
              "uuid": "auto_will_clark"
            },
            "summary": "This streamlines CI runner selection, potentially improving the efficiency of automated tests.",
            "importance": 14
          },
          {
            "number": 35503,
            "title": "guix: CMake-related improvements",
            "author": {
              "username": "hebasto",
              "uuid": "can_hennadii_stepanov"
            },
            "summary": "This PR enhances CMake integration within Guix, benefiting deterministic builds for developers.",
            "importance": 10
          },
          {
            "number": 35520,
            "title": "lint: remove redundant test suite uniqueness check",
            "author": {
              "username": "l0rinc",
              "uuid": "can_lorinc_pap"
            },
            "summary": "This refines the linting process by removing a redundant test suite uniqueness check.",
            "importance": 8
          },
          {
            "number": 35396,
            "title": "ci: Rewrite broken wrap-valgrind.sh to .py",
            "author": {
              "username": "maflcko",
              "uuid": "can_marcofalke"
            },
            "summary": "Rewriting the Valgrind wrapper to Python improves the reliability of memory error detection in CI.",
            "importance": 7
          },
          {
            "number": 35547,
            "title": "lint: Require scripted-diff script to succeed",
            "author": {
              "username": "hodlinator",
              "uuid": "can_hodlinator"
            },
            "summary": "This enforces stricter quality checks for scripted-diffs, improving code maintainability.",
            "importance": 6
          },
          {
            "number": 35526,
            "title": "ci: bump MSan fuzz timeout from 150 to 180 minutes",
            "author": {
              "username": "Sjors",
              "uuid": "can_sjors_provoost"
            },
            "summary": "Increasing the MSan fuzz test timeout allows for more thorough detection of potential bugs.",
            "importance": 5
          },
          {
            "number": 35540,
            "title": "test: descriptor: bare multisig at TOP level with exactly 3 pubkeys is allowed",
            "author": {
              "username": "brunoerg",
              "uuid": "can_bruno_garcia"
            },
            "summary": "This clarifies and corrects the behavior for bare multisig descriptors with three pubkeys, relevant for wallet developers.",
            "importance": 3
          },
          {
            "number": 35463,
            "title": "depends: Drop trailing slash from `CMAKE_INSTALL_LIBDIR`",
            "author": {
              "username": "hebasto",
              "uuid": "can_hennadii_stepanov"
            },
            "summary": "This minor build system fix standardizes library installation paths for better compatibility.",
            "importance": 3
          },
          {
            "number": 35546,
            "title": "ci: Use GCC consistently in i686 task",
            "author": {
              "username": "maflcko",
              "uuid": "can_marcofalke"
            },
            "summary": "This ensures consistent use of GCC in i686 CI tasks, improving build reliability.",
            "importance": 3
          },
          {
            "number": 35538,
            "title": "test: make TestChain100Setup's m_clock timestamp more readable",
            "author": {
              "username": "HowHsu",
              "uuid": "auto_hao_xu"
            },
            "summary": "This improves the readability of test timestamps, making development and debugging easier.",
            "importance": 3
          },
          {
            "number": 1865,
            "title": "test: enable -Wunused-function in test suite (Fix #1831)",
            "author": {
              "username": "kallal79",
              "uuid": "auto_kallal79"
            },
            "summary": "Enabling a new compiler warning in the test suite helps identify and remove unused code, improving overall quality.",
            "importance": 14
          },
          {
            "number": 1867,
            "title": "test: musig: fix dead \"aggnonce encodes two points at infinity\" check",
            "author": {
              "username": "theStack",
              "uuid": "can_sebastian_falbesoner"
            },
            "summary": "This fixes a test related to MuSig nonce validation, ensuring correctness for future Schnorr-related implementations.",
            "importance": 8
          }
        ]
      },
      {
        "name": "\ud83d\udee1\ufe0f Consensus & Cryptography",
        "prs": [
          {
            "number": 1859,
            "title": "field: force-inline 5x52 mul and sqr",
            "author": {
              "username": "l0rinc",
              "uuid": "can_lorinc_pap"
            },
            "summary": "This optimizes field arithmetic operations, potentially improving the performance of cryptographic computations.",
            "importance": 35
          }
        ]
      },
      {
        "name": "\ud83d\udd04 Misc / Other",
        "prs": [
          {
            "number": 35173,
            "title": "util: shorten thread names to avoid Linux truncation",
            "author": {
              "username": "l0rinc",
              "uuid": "can_lorinc_pap"
            },
            "summary": "Shortening thread names improves debuggability on Linux by preventing name truncation in system tools.",
            "importance": 27
          },
          {
            "number": 35470,
            "title": "argsman: Prevent duplicate option registration across categories",
            "author": {
              "username": "pablomartin4btc",
              "uuid": "auto_pablo_martin"
            },
            "summary": "This prevents duplicate registration of configuration options, enhancing the robustness of command-line argument parsing.",
            "importance": 9
          }
        ]
      }
    ],
    "hot": [
      {
        "name": "\ud83d\udd04 Misc / Other",
        "prs": [
          {
            "number": 1859,
            "title": "add LOCK() for proxy related data-structures",
            "author": "Diapolo",
            "event_count": 13
          },
          {
            "number": 1859,
            "title": "field: force-inline 5x52 mul and sqr",
            "author": "l0rinc",
            "event_count": 13
          },
          {
            "number": 35173,
            "title": "util: shorten thread names to avoid Linux truncation",
            "author": "l0rinc",
            "event_count": 11
          },
          {
            "number": 35496,
            "title": "kernel: add `btck_set_mock_time` for testing time-dependent paths",
            "author": "stringintech",
            "event_count": 9
          },
          {
            "number": 35511,
            "title": "RFC: consensus: Make `CAmount` a class",
            "author": "hodlinator",
            "event_count": 7
          },
          {
            "number": 35531,
            "title": "txindex: use 5-byte siphash keys to optimize disk usage",
            "author": "andrewtoth",
            "event_count": 7
          }
        ]
      }
    ]
  },
  "discussions": [
    {
      "source": "Delving",
      "subject": "Re: Fountain Codes: a way to reduce blockchain storage costs",
      "author": "Anthony Towns",
      "link": "https://delvingbitcoin.org/t/fountain-codes-a-way-to-reduce-blockchain-storage-costs/2624/2",
      "message_count": 8,
      "summary": "This thread discusses Fountain Codes as a novel approach to significantly reduce the storage requirements for Bitcoin full nodes. By allowing nodes to store only a fraction of the blockchain while ensuring data availability, this could enhance node accessibility and decentralization."
    },
    {
      "source": "Delving",
      "subject": "Re: State of the transaction privacy work in Bitcoin",
      "author": "Nikita Karetnikov",
      "link": "https://delvingbitcoin.org/t/state-of-the-transaction-privacy-work-in-bitcoin/2622/2",
      "message_count": 8,
      "summary": "This discussion provides an update on the ongoing efforts and various proposals aimed at enhancing transaction privacy within the Bitcoin protocol. Participants review the current state of privacy improvements, technical challenges, and future directions for better fungibility."
    }
  ],
  "shoutouts": {
    "new_contributors": [
      {
        "username": "kallal79",
        "uuid": "auto_kallal79"
      }
    ],
    "top_authors": [
      {
        "user": {
          "username": "hebasto",
          "uuid": "can_hennadii_stepanov"
        },
        "count": 3
      },
      {
        "user": {
          "username": "l0rinc",
          "uuid": "can_lorinc_pap"
        },
        "count": 3
      },
      {
        "user": {
          "username": "maflcko",
          "uuid": "can_marcofalke"
        },
        "count": 2
      },
      {
        "user": {
          "username": "HowHsu",
          "uuid": "auto_hao_xu"
        },
        "count": 1
      },
      {
        "user": {
          "username": "Sjors",
          "uuid": "can_sjors_provoost"
        },
        "count": 1
      }
    ],
    "top_reviewers": [
      {
        "user": {
          "username": "maflcko",
          "uuid": "can_marcofalke"
        },
        "count": 21
      },
      {
        "user": {
          "username": "fanquake",
          "uuid": "can_michael_ford"
        },
        "count": 15
      },
      {
        "user": {
          "username": "ryanofsky",
          "uuid": "can_russell_yanofsky"
        },
        "count": 15
      },
      {
        "user": {
          "username": "real-or-random",
          "uuid": "can_tim_ruffing"
        },
        "count": 14
      },
      {
        "user": {
          "username": "hebasto",
          "uuid": "can_hennadii_stepanov"
        },
        "count": 14
      }
    ],
    "all_active": [
      {
        "username": "ajtowns",
        "uuid": "can_anthony_towns"
      },
      {
        "username": "andrewtoth",
        "uuid": "can_andrew_toth"
      },
      {
        "username": "brunoerg",
        "uuid": "can_bruno_garcia"
      },
      {
        "username": "danielabrozzoni",
        "uuid": "auto_daniela_brozzoni"
      },
      {
        "username": "darosior",
        "uuid": "can_antoine_poinsot"
      },
      {
        "username": "edilmedeiros",
        "uuid": "auto_jos_edil_guimar_es_de_medeiros"
      },
      {
        "username": "fanquake",
        "uuid": "can_michael_ford"
      },
      {
        "username": "fernandguil",
        "uuid": "auto_guillermo_fernandes"
      },
      {
        "username": "furszy",
        "uuid": "auto_matias_furszyfer"
      },
      {
        "username": "hebasto",
        "uuid": "can_hennadii_stepanov"
      },
      {
        "username": "hodlinator",
        "uuid": "can_hodlinator"
      },
      {
        "username": "HowHsu",
        "uuid": "auto_hao_xu"
      },
      {
        "username": "instagibbs",
        "uuid": "can_greg_sanders"
      },
      {
        "username": "ismaelsadeeq",
        "uuid": "can_abubakar_sadiq_ismail"
      },
      {
        "username": "janb84",
        "uuid": "auto_jan_b"
      },
      {
        "username": "Jay-1409",
        "uuid": "auto_jay_1409"
      },
      {
        "username": "josibake",
        "uuid": "auto_oghenovo_usiwoma"
      },
      {
        "username": "kallal79",
        "uuid": "auto_kallal79"
      },
      {
        "username": "l0rinc",
        "uuid": "can_lorinc_pap"
      },
      {
        "username": "m3dwards",
        "uuid": "auto_max_edwards"
      },
      {
        "username": "maflcko",
        "uuid": "can_marcofalke"
      },
      {
        "username": "mzumsande",
        "uuid": "can_martin_zumsande"
      },
      {
        "username": "nervana21",
        "uuid": "auto_nervana21"
      },
      {
        "username": "optout21",
        "uuid": "auto_optout21"
      },
      {
        "username": "pablomartin4btc",
        "uuid": "auto_pablo_martin"
      },
      {
        "username": "pseudoramdom",
        "uuid": "auto_pseudoramdom"
      },
      {
        "username": "real-or-random",
        "uuid": "can_tim_ruffing"
      },
      {
        "username": "rkrux",
        "uuid": "auto_rkrux"
      },
      {
        "username": "ryanofsky",
        "uuid": "can_russell_yanofsky"
      },
      {
        "username": "sedited",
        "uuid": "auto_sebastian_kung"
      },
      {
        "username": "ShauryaaSharma",
        "uuid": "auto_shauryaasharma"
      },
      {
        "username": "sipa",
        "uuid": "can_pieter_wuille"
      },
      {
        "username": "siv2r",
        "uuid": "auto_sivaram_dhakshinamoorthy"
      },
      {
        "username": "Sjors",
        "uuid": "can_sjors_provoost"
      },
      {
        "username": "stickies-v",
        "uuid": "auto_stickies_v"
      },
      {
        "username": "stringintech",
        "uuid": "auto_stringintech"
      },
      {
        "username": "theStack",
        "uuid": "can_sebastian_falbesoner"
      },
      {
        "username": "theuni",
        "uuid": "can_cory_fields"
      },
      {
        "username": "tobtoht",
        "uuid": "auto_tobtoht"
      },
      {
        "username": "vasild",
        "uuid": "can_vasil_dimov"
      },
      {
        "username": "w0xlt",
        "uuid": "auto_woltx"
      },
      {
        "username": "willcl-ark",
        "uuid": "auto_will_clark"
      },
      {
        "username": "winterrdog",
        "uuid": "auto_winterrdog"
      }
    ]
  }
}